README.md
setup.py
ag/__init__.py
ag/ag.py
brokkk.egg-info/PKG-INFO
brokkk.egg-info/SOURCES.txt
brokkk.egg-info/dependency_links.txt
brokkk.egg-info/top_level.txt
ms/__init__.py
ms/mobinsarmaye.py