Metadata-Version: 2.1
Name: brokkk
Version: 2.0
Summary: description
Home-page: UNKNOWN
Author: M.Mortaz,M.Moalaghi
Author-email: hdhshd@dd.com
License: UNKNOWN
Platform: UNKNOWN
